[
    {
        "id": "ae0491bb.4f1eb",
        "type": "subflow",
        "name": "tv_screen_off_mode_on",
        "info": "",
        "category": "",
        "in": [
            {
                "x": 40,
                "y": 100,
                "wires": [
                    {
                        "id": "8818e636f63e70c7"
                    },
                    {
                        "id": "9c8540912fe0314a"
                    },
                    {
                        "id": "4d611ca80c166571"
                    },
                    {
                        "id": "e324372da3a76b29"
                    }
                ]
            }
        ],
        "out": [],
        "env": [],
        "meta": {},
        "color": "#DDAA99"
    },
    {
        "id": "be65f0d63b84b58c",
        "type": "api-call-service",
        "z": "ae0491bb.4f1eb",
        "name": "turn on shield",
        "server": "4ba92433.2478cc",
        "version": 5,
        "debugenabled": false,
        "domain": "media_player",
        "service": "turn_on",
        "areaId": [],
        "deviceId": [
            "aa1a5fa6d13fc3224345d871874f8619"
        ],
        "entityId": [
            "media_player.shield"
        ],
        "data": "",
        "dataType": "jsonata",
        "mergeContext": "",
        "mustacheAltTags": false,
        "outputProperties": [],
        "queue": "none",
        "x": 380,
        "y": 160,
        "wires": [
            []
        ]
    },
    {
        "id": "87a4edd77543d7f3",
        "type": "api-call-service",
        "z": "ae0491bb.4f1eb",
        "name": "turn on input boolean music",
        "server": "4ba92433.2478cc",
        "version": 5,
        "debugenabled": false,
        "domain": "input_boolean",
        "service": "turn_on",
        "areaId": [],
        "deviceId": [],
        "entityId": [
            "input_boolean.music"
        ],
        "data": "",
        "dataType": "json",
        "mergeContext": "",
        "mustacheAltTags": false,
        "outputProperties": [],
        "queue": "none",
        "x": 480,
        "y": 220,
        "wires": [
            []
        ]
    },
    {
        "id": "9c8540912fe0314a",
        "type": "api-current-state",
        "z": "ae0491bb.4f1eb",
        "name": "state input boolean tv off",
        "server": "4ba92433.2478cc",
        "version": 3,
        "outputs": 2,
        "halt_if": "off",
        "halt_if_type": "str",
        "halt_if_compare": "is",
        "entity_id": "input_boolean.music",
        "state_type": "str",
        "blockInputOverrides": true,
        "outputProperties": [
            {
                "property": "payload",
                "propertyType": "msg",
                "value": "",
                "valueType": "entityState"
            },
            {
                "property": "data",
                "propertyType": "msg",
                "value": "",
                "valueType": "entity"
            }
        ],
        "for": 0,
        "forType": "num",
        "forUnits": "minutes",
        "x": 230,
        "y": 220,
        "wires": [
            [
                "87a4edd77543d7f3"
            ],
            []
        ]
    },
    {
        "id": "8818e636f63e70c7",
        "type": "api-current-state",
        "z": "ae0491bb.4f1eb",
        "name": "state shield off",
        "server": "4ba92433.2478cc",
        "version": 3,
        "outputs": 2,
        "halt_if": "off",
        "halt_if_type": "str",
        "halt_if_compare": "is",
        "entity_id": "media_player.shield",
        "state_type": "str",
        "blockInputOverrides": false,
        "outputProperties": [
            {
                "property": "payload",
                "propertyType": "msg",
                "value": "",
                "valueType": "entityState"
            },
            {
                "property": "data",
                "propertyType": "msg",
                "value": "",
                "valueType": "entity"
            }
        ],
        "for": "0",
        "forType": "num",
        "forUnits": "minutes",
        "override_topic": false,
        "state_location": "payload",
        "override_payload": "msg",
        "entity_location": "data",
        "override_data": "msg",
        "x": 200,
        "y": 160,
        "wires": [
            [
                "be65f0d63b84b58c"
            ],
            []
        ]
    },
    {
        "id": "4d611ca80c166571",
        "type": "api-call-service",
        "z": "ae0491bb.4f1eb",
        "name": "turn on receiver",
        "server": "4ba92433.2478cc",
        "version": 5,
        "debugenabled": false,
        "domain": "remote",
        "service": "send_command",
        "areaId": [],
        "deviceId": [
            "34a73fe47cda5c964dcb946e48f8a307"
        ],
        "entityId": [
            "remote.harmony_hub_01"
        ],
        "data": "{\"device\":\"53126254\",\"command\":\"PowerOn\"}",
        "dataType": "json",
        "mergeContext": "",
        "mustacheAltTags": false,
        "outputProperties": [],
        "queue": "none",
        "x": 200,
        "y": 280,
        "wires": [
            []
        ]
    },
    {
        "id": "0cb67556a76c3eb6",
        "type": "api-call-service",
        "z": "ae0491bb.4f1eb",
        "name": "turn off screen",
        "server": "4ba92433.2478cc",
        "version": 5,
        "debugenabled": false,
        "domain": "webostv",
        "service": "command",
        "areaId": [],
        "deviceId": [],
        "entityId": [
            "media_player.lg_webos_smart_tv"
        ],
        "data": "{\"command\":\"com.webos.service.tvpower/power/turnOffScreen\"}",
        "dataType": "json",
        "mergeContext": "",
        "mustacheAltTags": false,
        "outputProperties": [],
        "queue": "none",
        "x": 460,
        "y": 100,
        "wires": [
            []
        ]
    },
    {
        "id": "e324372da3a76b29",
        "type": "ha-wait-until",
        "z": "ae0491bb.4f1eb",
        "name": "wait until tv mediaplayer is on",
        "server": "4ba92433.2478cc",
        "version": 2,
        "outputs": 1,
        "entityId": "media_player.lg_webos_smart_tv",
        "entityIdFilterType": "exact",
        "property": "state",
        "comparator": "is",
        "value": "on",
        "valueType": "str",
        "timeout": "0",
        "timeoutType": "num",
        "timeoutUnits": "seconds",
        "checkCurrentState": true,
        "blockInputOverrides": true,
        "outputProperties": [],
        "entityLocation": "data",
        "entityLocationType": "none",
        "x": 240,
        "y": 100,
        "wires": [
            [
                "0cb67556a76c3eb6"
            ]
        ]
    },
    {
        "id": "54d7a449b5482909",
        "type": "comment",
        "z": "ae0491bb.4f1eb",
        "name": "turn on tv and turn off screen for low energy usage",
        "info": "",
        "x": 210,
        "y": 40,
        "wires": []
    },
    {
        "id": "0f710598d50e0596",
        "type": "subflow",
        "name": "tv_mode_off",
        "info": "",
        "category": "",
        "in": [
            {
                "x": 40,
                "y": 40,
                "wires": [
                    {
                        "id": "19c16b81a65ce03d"
                    },
                    {
                        "id": "7d78624dbc489f07"
                    },
                    {
                        "id": "f0aeb0277f95eebd"
                    },
                    {
                        "id": "f69679ab2ccbee4f"
                    },
                    {
                        "id": "1f164f2207e30219"
                    },
                    {
                        "id": "46e45a22c53e320a"
                    }
                ]
            }
        ],
        "out": [],
        "env": [],
        "meta": {},
        "color": "#DDAA99"
    },
    {
        "id": "19c16b81a65ce03d",
        "type": "api-call-service",
        "z": "0f710598d50e0596",
        "name": "turn off media players",
        "server": "4ba92433.2478cc",
        "version": 5,
        "debugenabled": false,
        "domain": "media_player",
        "service": "turn_off",
        "areaId": [],
        "deviceId": [],
        "entityId": [
            "media_player.home_speaker",
            "media_player.lg_webos_smart_tv",
            "media_player.lise_s_kamer",
            "media_player.shield"
        ],
        "data": "",
        "dataType": "jsonata",
        "mergeContext": "",
        "mustacheAltTags": false,
        "outputProperties": [],
        "queue": "none",
        "x": 220,
        "y": 40,
        "wires": [
            []
        ]
    },
    {
        "id": "7d78624dbc489f07",
        "type": "api-current-state",
        "z": "0f710598d50e0596",
        "name": "state input boolean tv is on",
        "server": "4ba92433.2478cc",
        "version": 3,
        "outputs": 2,
        "halt_if": "on",
        "halt_if_type": "str",
        "halt_if_compare": "is",
        "entity_id": "input_boolean.tv",
        "state_type": "str",
        "blockInputOverrides": true,
        "outputProperties": [
            {
                "property": "payload",
                "propertyType": "msg",
                "value": "",
                "valueType": "entityState"
            },
            {
                "property": "data",
                "propertyType": "msg",
                "value": "",
                "valueType": "entity"
            }
        ],
        "for": 0,
        "forType": "num",
        "forUnits": "minutes",
        "x": 240,
        "y": 340,
        "wires": [
            [
                "ed81a86bf1f06d72"
            ],
            []
        ]
    },
    {
        "id": "ed81a86bf1f06d72",
        "type": "api-call-service",
        "z": "0f710598d50e0596",
        "name": "turn off input boolean tv",
        "server": "4ba92433.2478cc",
        "version": 5,
        "debugenabled": false,
        "domain": "input_boolean",
        "service": "turn_off",
        "areaId": [],
        "deviceId": [],
        "entityId": [
            "input_boolean.tv"
        ],
        "data": "",
        "dataType": "json",
        "mergeContext": "",
        "mustacheAltTags": false,
        "outputProperties": [],
        "queue": "none",
        "x": 510,
        "y": 340,
        "wires": [
            []
        ]
    },
    {
        "id": "f0aeb0277f95eebd",
        "type": "api-current-state",
        "z": "0f710598d50e0596",
        "name": "state input boolean music is on",
        "server": "4ba92433.2478cc",
        "version": 3,
        "outputs": 2,
        "halt_if": "on",
        "halt_if_type": "str",
        "halt_if_compare": "is",
        "entity_id": "input_boolean.music",
        "state_type": "str",
        "blockInputOverrides": true,
        "outputProperties": [
            {
                "property": "payload",
                "propertyType": "msg",
                "value": "",
                "valueType": "entityState"
            },
            {
                "property": "data",
                "propertyType": "msg",
                "value": "",
                "valueType": "entity"
            }
        ],
        "for": 0,
        "forType": "num",
        "forUnits": "minutes",
        "x": 250,
        "y": 400,
        "wires": [
            [
                "7df266f8e004a08d"
            ],
            []
        ]
    },
    {
        "id": "7df266f8e004a08d",
        "type": "api-call-service",
        "z": "0f710598d50e0596",
        "name": "turn off input boolean music",
        "server": "4ba92433.2478cc",
        "version": 5,
        "debugenabled": false,
        "domain": "input_boolean",
        "service": "turn_off",
        "areaId": [],
        "deviceId": [],
        "entityId": [
            "input_boolean.music"
        ],
        "data": "",
        "dataType": "json",
        "mergeContext": "",
        "mustacheAltTags": false,
        "outputProperties": [],
        "queue": "none",
        "x": 520,
        "y": 400,
        "wires": [
            []
        ]
    },
    {
        "id": "f69679ab2ccbee4f",
        "type": "api-call-service",
        "z": "0f710598d50e0596",
        "name": "select radio uit",
        "server": "4ba92433.2478cc",
        "version": 5,
        "debugenabled": false,
        "domain": "input_select",
        "service": "select_option",
        "areaId": [],
        "deviceId": [],
        "entityId": [
            "input_select.radio_station"
        ],
        "data": "{\"option\":\"Radio Uit\"}",
        "dataType": "json",
        "mergeContext": "",
        "mustacheAltTags": false,
        "outputProperties": [],
        "queue": "none",
        "x": 200,
        "y": 220,
        "wires": [
            []
        ]
    },
    {
        "id": "1f164f2207e30219",
        "type": "api-call-service",
        "z": "0f710598d50e0596",
        "name": "select spotify uit",
        "server": "4ba92433.2478cc",
        "version": 5,
        "debugenabled": false,
        "domain": "input_select",
        "service": "select_option",
        "areaId": [],
        "deviceId": [],
        "entityId": [
            "input_select.spotify_playlist"
        ],
        "data": "{\"option\":\"Spotify Uit\"}",
        "dataType": "json",
        "mergeContext": "",
        "mustacheAltTags": false,
        "outputProperties": [],
        "queue": "none",
        "x": 200,
        "y": 280,
        "wires": [
            []
        ]
    },
    {
        "id": "6a12c49028cb62b2",
        "type": "api-call-service",
        "z": "0f710598d50e0596",
        "name": "turn off tv",
        "server": "4ba92433.2478cc",
        "version": 5,
        "debugenabled": false,
        "domain": "webostv",
        "service": "command",
        "areaId": [],
        "deviceId": [],
        "entityId": [
            "media_player.lg_webos_smart_tv"
        ],
        "data": "{\"command\":\"system/turnOff\"}",
        "dataType": "json",
        "mergeContext": "",
        "mustacheAltTags": false,
        "outputProperties": [],
        "queue": "none",
        "x": 180,
        "y": 100,
        "wires": [
            []
        ]
    },
    {
        "id": "46e45a22c53e320a",
        "type": "api-call-service",
        "z": "0f710598d50e0596",
        "name": "turn off reciever",
        "server": "4ba92433.2478cc",
        "version": 5,
        "debugenabled": false,
        "domain": "remote",
        "service": "send_command",
        "areaId": [
            "living_room"
        ],
        "deviceId": [
            "34a73fe47cda5c964dcb946e48f8a307"
        ],
        "entityId": [
            "remote.harmony_hub_01"
        ],
        "data": "{\"device\":\"53126254\",\"command\":\"PowerOff\"}",
        "dataType": "json",
        "mergeContext": "",
        "mustacheAltTags": false,
        "outputProperties": [],
        "queue": "none",
        "x": 200,
        "y": 160,
        "wires": [
            []
        ]
    },
    {
        "id": "9ed9ce7ce8f74ca0",
        "type": "subflow",
        "name": "tv_mode_on",
        "info": "",
        "category": "",
        "in": [
            {
                "x": 40,
                "y": 100,
                "wires": [
                    {
                        "id": "cbffe613f7b4d2cd"
                    },
                    {
                        "id": "ab941695962a49ca"
                    },
                    {
                        "id": "39676675d41d2349"
                    },
                    {
                        "id": "71594be305815ee3"
                    },
                    {
                        "id": "f03069dd7ff849fa"
                    }
                ]
            }
        ],
        "out": [],
        "env": [],
        "meta": {},
        "color": "#DDAA99"
    },
    {
        "id": "cbffe613f7b4d2cd",
        "type": "api-current-state",
        "z": "9ed9ce7ce8f74ca0",
        "name": "state shield is not on",
        "server": "4ba92433.2478cc",
        "version": 3,
        "outputs": 2,
        "halt_if": "on",
        "halt_if_type": "str",
        "halt_if_compare": "is_not",
        "entity_id": "media_player.shield",
        "state_type": "str",
        "blockInputOverrides": false,
        "outputProperties": [
            {
                "property": "payload",
                "propertyType": "msg",
                "value": "",
                "valueType": "entityState"
            },
            {
                "property": "data",
                "propertyType": "msg",
                "value": "",
                "valueType": "entity"
            }
        ],
        "for": "0",
        "forType": "num",
        "forUnits": "minutes",
        "override_topic": false,
        "state_location": "payload",
        "override_payload": "msg",
        "entity_location": "data",
        "override_data": "msg",
        "x": 220,
        "y": 100,
        "wires": [
            [
                "210448aceed6c74e"
            ],
            []
        ]
    },
    {
        "id": "210448aceed6c74e",
        "type": "api-call-service",
        "z": "9ed9ce7ce8f74ca0",
        "name": "turn on shield",
        "server": "4ba92433.2478cc",
        "version": 5,
        "debugenabled": false,
        "domain": "media_player",
        "service": "turn_on",
        "areaId": [],
        "deviceId": [
            "aa1a5fa6d13fc3224345d871874f8619"
        ],
        "entityId": [
            "media_player.shield"
        ],
        "data": "",
        "dataType": "jsonata",
        "mergeContext": "",
        "mustacheAltTags": false,
        "outputProperties": [],
        "queue": "none",
        "x": 460,
        "y": 100,
        "wires": [
            []
        ]
    },
    {
        "id": "e5c0ae3969af85fb",
        "type": "comment",
        "z": "9ed9ce7ce8f74ca0",
        "name": "turn on tv, shield mediaplayer and receiver",
        "info": "",
        "x": 180,
        "y": 40,
        "wires": []
    },
    {
        "id": "ab941695962a49ca",
        "type": "api-current-state",
        "z": "9ed9ce7ce8f74ca0",
        "name": "state input boolean tv is off",
        "server": "4ba92433.2478cc",
        "version": 3,
        "outputs": 2,
        "halt_if": "off",
        "halt_if_type": "str",
        "halt_if_compare": "is",
        "entity_id": "input_boolean.tv",
        "state_type": "str",
        "blockInputOverrides": true,
        "outputProperties": [
            {
                "property": "payload",
                "propertyType": "msg",
                "value": "",
                "valueType": "entityState"
            },
            {
                "property": "data",
                "propertyType": "msg",
                "value": "",
                "valueType": "entity"
            }
        ],
        "for": 0,
        "forType": "num",
        "forUnits": "minutes",
        "x": 240,
        "y": 140,
        "wires": [
            [
                "c5696bd905d5d0b2"
            ],
            []
        ]
    },
    {
        "id": "c5696bd905d5d0b2",
        "type": "api-call-service",
        "z": "9ed9ce7ce8f74ca0",
        "name": "turn on input boolean tv",
        "server": "4ba92433.2478cc",
        "version": 5,
        "debugenabled": false,
        "domain": "input_boolean",
        "service": "turn_on",
        "areaId": [],
        "deviceId": [],
        "entityId": [
            "input_boolean.tv"
        ],
        "data": "",
        "dataType": "json",
        "mergeContext": "",
        "mustacheAltTags": false,
        "outputProperties": [],
        "queue": "none",
        "x": 490,
        "y": 140,
        "wires": [
            []
        ]
    },
    {
        "id": "39676675d41d2349",
        "type": "api-call-service",
        "z": "9ed9ce7ce8f74ca0",
        "name": "turn on receiver",
        "server": "4ba92433.2478cc",
        "version": 5,
        "debugenabled": false,
        "domain": "remote",
        "service": "send_command",
        "areaId": [],
        "deviceId": [
            "34a73fe47cda5c964dcb946e48f8a307"
        ],
        "entityId": [
            "remote.harmony_hub_01"
        ],
        "data": "{\"device\":\"53126254\",\"command\":\"PowerOn\"}",
        "dataType": "json",
        "mergeContext": "",
        "mustacheAltTags": false,
        "outputProperties": [],
        "queue": "none",
        "x": 200,
        "y": 220,
        "wires": [
            []
        ]
    },
    {
        "id": "71594be305815ee3",
        "type": "api-call-service",
        "z": "9ed9ce7ce8f74ca0",
        "name": "turn on screen",
        "server": "4ba92433.2478cc",
        "version": 5,
        "debugenabled": false,
        "domain": "webostv",
        "service": "command",
        "areaId": [],
        "deviceId": [],
        "entityId": [
            "media_player.lg_webos_smart_tv"
        ],
        "data": "{\"command\":\"com.webos.service.tvpower/power/turnOnScreen\"}",
        "dataType": "json",
        "mergeContext": "",
        "mustacheAltTags": false,
        "outputProperties": [],
        "queue": "none",
        "x": 200,
        "y": 260,
        "wires": [
            []
        ]
    },
    {
        "id": "f03069dd7ff849fa",
        "type": "api-call-service",
        "z": "9ed9ce7ce8f74ca0",
        "name": "input select radio uit",
        "server": "4ba92433.2478cc",
        "version": 5,
        "debugenabled": false,
        "domain": "input_select",
        "service": "select_option",
        "areaId": [],
        "deviceId": [],
        "entityId": [
            "input_select.radio_station"
        ],
        "data": "{\"option\":\"Radio Uit\"}",
        "dataType": "json",
        "mergeContext": "",
        "mustacheAltTags": false,
        "outputProperties": [],
        "queue": "none",
        "x": 220,
        "y": 180,
        "wires": [
            []
        ]
    },
    {
        "id": "79866c45b34ebc3c",
        "type": "tab",
        "label": "entertainment_v2",
        "disabled": false,
        "info": "",
        "env": []
    },
    {
        "id": "dc4e841346f4b5e1",
        "type": "comment",
        "z": "79866c45b34ebc3c",
        "name": "tv and media entertaiment automations",
        "info": "",
        "x": 170,
        "y": 20,
        "wires": []
    },
    {
        "id": "5e38856a1976c85e",
        "type": "server-state-changed",
        "z": "79866c45b34ebc3c",
        "name": "state input select harmony hub",
        "server": "4ba92433.2478cc",
        "version": 4,
        "exposeToHomeAssistant": false,
        "haConfig": [
            {
                "property": "name",
                "value": ""
            },
            {
                "property": "icon",
                "value": ""
            }
        ],
        "entityidfilter": "input_select.entertainment_activity",
        "entityidfiltertype": "exact",
        "outputinitially": false,
        "state_type": "str",
        "haltifstate": "",
        "halt_if_type": "str",
        "halt_if_compare": "is",
        "outputs": 1,
        "output_only_on_state_change": true,
        "for": "",
        "forType": "num",
        "forUnits": "minutes",
        "ignorePrevStateNull": false,
        "ignorePrevStateUnknown": true,
        "ignorePrevStateUnavailable": true,
        "ignoreCurrentStateUnknown": true,
        "ignoreCurrentStateUnavailable": true,
        "outputProperties": [
            {
                "property": "payload",
                "propertyType": "msg",
                "value": "",
                "valueType": "entityState"
            },
            {
                "property": "data",
                "propertyType": "msg",
                "value": "",
                "valueType": "eventData"
            },
            {
                "property": "topic",
                "propertyType": "msg",
                "value": "",
                "valueType": "triggerId"
            }
        ],
        "x": 150,
        "y": 100,
        "wires": [
            [
                "9c3fb5b7a33f4cfe"
            ]
        ]
    },
    {
        "id": "9c3fb5b7a33f4cfe",
        "type": "switch",
        "z": "79866c45b34ebc3c",
        "name": "input select media activity",
        "property": "data.new_state.state",
        "propertyType": "msg",
        "rules": [
            {
                "t": "eq",
                "v": "Uitschakelen",
                "vt": "str"
            },
            {
                "t": "eq",
                "v": "TV",
                "vt": "str"
            },
            {
                "t": "eq",
                "v": "Radio",
                "vt": "str"
            }
        ],
        "checkall": "true",
        "repair": false,
        "outputs": 3,
        "x": 430,
        "y": 100,
        "wires": [
            [
                "c0e461ba205d827d"
            ],
            [
                "6899ab80b8f4ccfd"
            ],
            [
                "b6c13f3e88d196d9",
                "7602bd2250b367d8"
            ]
        ]
    },
    {
        "id": "419130d9cbaac3b6",
        "type": "comment",
        "z": "79866c45b34ebc3c",
        "name": "frontend activity input select",
        "info": "",
        "x": 160,
        "y": 60,
        "wires": []
    },
    {
        "id": "e16e36f693cd77e6",
        "type": "switch",
        "z": "79866c45b34ebc3c",
        "name": "App Name ",
        "property": "data.new_state.attributes.app_name",
        "propertyType": "msg",
        "rules": [
            {
                "t": "cont",
                "v": "NLZIET",
                "vt": "str"
            },
            {
                "t": "cont",
                "v": "Videoland",
                "vt": "str"
            },
            {
                "t": "cont",
                "v": "YouTube",
                "vt": "str"
            },
            {
                "t": "cont",
                "v": "Spotify",
                "vt": "str"
            },
            {
                "t": "cont",
                "v": "TuneIn Free",
                "vt": "str"
            }
        ],
        "checkall": "true",
        "repair": false,
        "outputs": 5,
        "x": 330,
        "y": 380,
        "wires": [
            [
                "11141d51e1cc0a89"
            ],
            [
                "11141d51e1cc0a89"
            ],
            [
                "11141d51e1cc0a89"
            ],
            [
                "8b1d0a3b99895a0c"
            ],
            [
                "8b1d0a3b99895a0c"
            ]
        ]
    },
    {
        "id": "21a8d478fc32a48b",
        "type": "server-state-changed",
        "z": "79866c45b34ebc3c",
        "name": "state media player shield",
        "server": "4ba92433.2478cc",
        "version": 4,
        "exposeToHomeAssistant": false,
        "haConfig": [
            {
                "property": "name",
                "value": ""
            },
            {
                "property": "icon",
                "value": ""
            }
        ],
        "entityidfilter": "media_player.shield",
        "entityidfiltertype": "exact",
        "outputinitially": true,
        "state_type": "str",
        "haltifstate": "",
        "halt_if_type": "str",
        "halt_if_compare": "is",
        "outputs": 1,
        "output_only_on_state_change": true,
        "for": "800",
        "forType": "num",
        "forUnits": "milliseconds",
        "ignorePrevStateNull": false,
        "ignorePrevStateUnknown": true,
        "ignorePrevStateUnavailable": true,
        "ignoreCurrentStateUnknown": true,
        "ignoreCurrentStateUnavailable": true,
        "outputProperties": [
            {
                "property": "payload",
                "propertyType": "msg",
                "value": "",
                "valueType": "entityState"
            },
            {
                "property": "data",
                "propertyType": "msg",
                "value": "",
                "valueType": "eventData"
            },
            {
                "property": "topic",
                "propertyType": "msg",
                "value": "",
                "valueType": "triggerId"
            }
        ],
        "x": 130,
        "y": 360,
        "wires": [
            [
                "e16e36f693cd77e6"
            ]
        ]
    },
    {
        "id": "90aa7330b7dcb647",
        "type": "api-call-service",
        "z": "79866c45b34ebc3c",
        "name": "input select tv",
        "server": "4ba92433.2478cc",
        "version": 5,
        "debugenabled": false,
        "domain": "input_select",
        "service": "select_option",
        "areaId": [],
        "deviceId": [],
        "entityId": [
            "input_select.entertainment_activity"
        ],
        "data": "{\"option\":\"TV\"}",
        "dataType": "json",
        "mergeContext": "",
        "mustacheAltTags": false,
        "outputProperties": [],
        "queue": "none",
        "x": 880,
        "y": 360,
        "wires": [
            []
        ]
    },
    {
        "id": "11141d51e1cc0a89",
        "type": "api-current-state",
        "z": "79866c45b34ebc3c",
        "name": "input select media source livingroom tv",
        "server": "4ba92433.2478cc",
        "version": 3,
        "outputs": 2,
        "halt_if": "Woonkamer TV",
        "halt_if_type": "str",
        "halt_if_compare": "is",
        "entity_id": "input_select.mediaplayer_destination",
        "state_type": "str",
        "blockInputOverrides": false,
        "outputProperties": [
            {
                "property": "input_select.mediaplayer_destination",
                "propertyType": "msg",
                "value": "",
                "valueType": "entityState"
            },
            {
                "property": "data",
                "propertyType": "msg",
                "value": "",
                "valueType": "entity"
            }
        ],
        "for": 0,
        "forType": "num",
        "forUnits": "minutes",
        "x": 610,
        "y": 360,
        "wires": [
            [
                "90aa7330b7dcb647"
            ],
            []
        ]
    },
    {
        "id": "8b1d0a3b99895a0c",
        "type": "api-current-state",
        "z": "79866c45b34ebc3c",
        "name": "input select media source livingroom tv",
        "server": "4ba92433.2478cc",
        "version": 3,
        "outputs": 2,
        "halt_if": "Woonkamer TV",
        "halt_if_type": "str",
        "halt_if_compare": "is",
        "entity_id": "input_select.mediaplayer_destination",
        "state_type": "str",
        "blockInputOverrides": false,
        "outputProperties": [
            {
                "property": "input_select.mediaplayer_destination",
                "propertyType": "msg",
                "value": "",
                "valueType": "entityState"
            },
            {
                "property": "data",
                "propertyType": "msg",
                "value": "",
                "valueType": "entity"
            }
        ],
        "for": "",
        "forType": "num",
        "forUnits": "seconds",
        "x": 610,
        "y": 420,
        "wires": [
            [
                "0b032a7e9e924f5e"
            ],
            []
        ]
    },
    {
        "id": "91ad59d63c5a49f3",
        "type": "api-current-state",
        "z": "79866c45b34ebc3c",
        "name": "state person coen home",
        "server": "4ba92433.2478cc",
        "version": 3,
        "outputs": 2,
        "halt_if": "home",
        "halt_if_type": "str",
        "halt_if_compare": "is",
        "entity_id": "person.coen",
        "state_type": "str",
        "blockInputOverrides": false,
        "outputProperties": [
            {
                "property": "payload",
                "propertyType": "msg",
                "value": "",
                "valueType": "entityState"
            },
            {
                "property": "data",
                "propertyType": "msg",
                "value": "",
                "valueType": "entity"
            }
        ],
        "for": 0,
        "forType": "num",
        "forUnits": "minutes",
        "override_topic": false,
        "state_location": "payload",
        "override_payload": "msg",
        "entity_location": "data",
        "override_data": "msg",
        "x": 370,
        "y": 1080,
        "wires": [
            [
                "47159d792a448631"
            ],
            []
        ]
    },
    {
        "id": "47159d792a448631",
        "type": "api-current-state",
        "z": "79866c45b34ebc3c",
        "name": "state media player shield playing",
        "server": "4ba92433.2478cc",
        "version": 3,
        "outputs": 2,
        "halt_if": "playing",
        "halt_if_type": "str",
        "halt_if_compare": "is",
        "entity_id": "media_player.shield",
        "state_type": "str",
        "blockInputOverrides": false,
        "outputProperties": [
            {
                "property": "payload",
                "propertyType": "msg",
                "value": "",
                "valueType": "entityState"
            },
            {
                "property": "data",
                "propertyType": "msg",
                "value": "",
                "valueType": "entity"
            }
        ],
        "for": 0,
        "forType": "num",
        "forUnits": "minutes",
        "override_topic": false,
        "state_location": "payload",
        "override_payload": "msg",
        "entity_location": "data",
        "override_data": "msg",
        "x": 650,
        "y": 1080,
        "wires": [
            [
                "057c6a119a6a4e2e",
                "5be0ace48ae1026a"
            ],
            []
        ]
    },
    {
        "id": "cd21f3c2a8ff9e38",
        "type": "api-current-state",
        "z": "79866c45b34ebc3c",
        "name": "state person anne home",
        "server": "4ba92433.2478cc",
        "version": 3,
        "outputs": 2,
        "halt_if": "home",
        "halt_if_type": "str",
        "halt_if_compare": "is",
        "entity_id": "person.anne",
        "state_type": "str",
        "blockInputOverrides": false,
        "outputProperties": [
            {
                "property": "payload",
                "propertyType": "msg",
                "value": "",
                "valueType": "entityState"
            },
            {
                "property": "data",
                "propertyType": "msg",
                "value": "",
                "valueType": "entity"
            }
        ],
        "for": 0,
        "forType": "num",
        "forUnits": "minutes",
        "override_topic": false,
        "state_location": "payload",
        "override_payload": "msg",
        "entity_location": "data",
        "override_data": "msg",
        "x": 370,
        "y": 1140,
        "wires": [
            [
                "47159d792a448631"
            ],
            []
        ]
    },
    {
        "id": "c1521a93f4823d6a",
        "type": "api-call-service",
        "z": "79866c45b34ebc3c",
        "name": "notify tv",
        "server": "4ba92433.2478cc",
        "version": 5,
        "debugenabled": false,
        "domain": "notify",
        "service": "lg_webos_smart_tv",
        "areaId": [],
        "deviceId": [],
        "entityId": [],
        "data": "{\"message\":\"{{{message}}}\",\"title\":\"Pauze\"}",
        "dataType": "json",
        "mergeContext": "",
        "mustacheAltTags": false,
        "outputProperties": [],
        "queue": "none",
        "x": 1040,
        "y": 1120,
        "wires": [
            []
        ]
    },
    {
        "id": "5be0ace48ae1026a",
        "type": "template",
        "z": "79866c45b34ebc3c",
        "name": "message",
        "field": "message",
        "fieldType": "msg",
        "format": "handlebars",
        "syntax": "mustache",
        "template": "TV gepauseerd i.v.m. telefoongesprek.",
        "output": "str",
        "x": 880,
        "y": 1140,
        "wires": [
            [
                "c1521a93f4823d6a",
                "087ff162e7a03e10"
            ]
        ]
    },
    {
        "id": "057c6a119a6a4e2e",
        "type": "api-call-service",
        "z": "79866c45b34ebc3c",
        "name": "pause shield",
        "server": "4ba92433.2478cc",
        "version": 5,
        "debugenabled": false,
        "domain": "media_player",
        "service": "media_pause",
        "areaId": [],
        "deviceId": [],
        "entityId": [
            "media_player.shield"
        ],
        "data": "",
        "dataType": "json",
        "mergeContext": "",
        "mustacheAltTags": false,
        "outputProperties": [],
        "queue": "none",
        "x": 890,
        "y": 1080,
        "wires": [
            []
        ]
    },
    {
        "id": "ee5c442a02a22dee",
        "type": "server-state-changed",
        "z": "79866c45b34ebc3c",
        "name": "state phone coen offhook",
        "server": "4ba92433.2478cc",
        "version": 4,
        "exposeToHomeAssistant": false,
        "haConfig": [
            {
                "property": "name",
                "value": ""
            },
            {
                "property": "icon",
                "value": ""
            }
        ],
        "entityidfilter": "sensor.phone_coen_phone_state",
        "entityidfiltertype": "exact",
        "outputinitially": true,
        "state_type": "str",
        "haltifstate": "offhook",
        "halt_if_type": "str",
        "halt_if_compare": "is",
        "outputs": 2,
        "output_only_on_state_change": true,
        "for": 0,
        "forType": "num",
        "forUnits": "minutes",
        "ignorePrevStateNull": true,
        "ignorePrevStateUnknown": true,
        "ignorePrevStateUnavailable": true,
        "ignoreCurrentStateUnknown": true,
        "ignoreCurrentStateUnavailable": true,
        "outputProperties": [
            {
                "property": "payload",
                "propertyType": "msg",
                "value": "",
                "valueType": "entityState"
            },
            {
                "property": "data",
                "propertyType": "msg",
                "value": "",
                "valueType": "eventData"
            },
            {
                "property": "topic",
                "propertyType": "msg",
                "value": "",
                "valueType": "triggerId"
            }
        ],
        "x": 130,
        "y": 1080,
        "wires": [
            [
                "91ad59d63c5a49f3"
            ],
            []
        ]
    },
    {
        "id": "b038607aa77e3f43",
        "type": "server-state-changed",
        "z": "79866c45b34ebc3c",
        "name": "state phone anne offhook",
        "server": "4ba92433.2478cc",
        "version": 4,
        "exposeToHomeAssistant": false,
        "haConfig": [
            {
                "property": "name",
                "value": ""
            },
            {
                "property": "icon",
                "value": ""
            }
        ],
        "entityidfilter": "sensor.phone_anne_phone_state_2",
        "entityidfiltertype": "exact",
        "outputinitially": true,
        "state_type": "str",
        "haltifstate": "offhook",
        "halt_if_type": "str",
        "halt_if_compare": "is",
        "outputs": 2,
        "output_only_on_state_change": true,
        "for": 0,
        "forType": "num",
        "forUnits": "minutes",
        "ignorePrevStateNull": true,
        "ignorePrevStateUnknown": true,
        "ignorePrevStateUnavailable": true,
        "ignoreCurrentStateUnknown": true,
        "ignoreCurrentStateUnavailable": true,
        "outputProperties": [
            {
                "property": "payload",
                "propertyType": "msg",
                "value": "",
                "valueType": "entityState"
            },
            {
                "property": "data",
                "propertyType": "msg",
                "value": "",
                "valueType": "eventData"
            },
            {
                "property": "topic",
                "propertyType": "msg",
                "value": "",
                "valueType": "triggerId"
            }
        ],
        "x": 130,
        "y": 1140,
        "wires": [
            [
                "cd21f3c2a8ff9e38"
            ],
            []
        ]
    },
    {
        "id": "09cac472270753b3",
        "type": "comment",
        "z": "79866c45b34ebc3c",
        "name": "pause when phone is off hook",
        "info": "",
        "x": 160,
        "y": 1040,
        "wires": []
    },
    {
        "id": "087ff162e7a03e10",
        "type": "link out",
        "z": "79866c45b34ebc3c",
        "name": "",
        "links": [
            "ebf4860d.603538"
        ],
        "x": 995,
        "y": 1180,
        "wires": []
    },
    {
        "id": "793f169c2c699456",
        "type": "server-state-changed",
        "z": "79866c45b34ebc3c",
        "name": "state input select radio station",
        "server": "4ba92433.2478cc",
        "version": 4,
        "exposeToHomeAssistant": false,
        "haConfig": [
            {
                "property": "name",
                "value": ""
            },
            {
                "property": "icon",
                "value": ""
            }
        ],
        "entityidfilter": "input_select.radio_station",
        "entityidfiltertype": "exact",
        "outputinitially": false,
        "state_type": "str",
        "haltifstate": "",
        "halt_if_type": "str",
        "halt_if_compare": "is",
        "outputs": 1,
        "output_only_on_state_change": true,
        "for": "",
        "forType": "num",
        "forUnits": "minutes",
        "ignorePrevStateNull": false,
        "ignorePrevStateUnknown": true,
        "ignorePrevStateUnavailable": true,
        "ignoreCurrentStateUnknown": true,
        "ignoreCurrentStateUnavailable": true,
        "outputProperties": [
            {
                "property": "payload",
                "propertyType": "msg",
                "value": "",
                "valueType": "entityState"
            },
            {
                "property": "data",
                "propertyType": "msg",
                "value": "",
                "valueType": "eventData"
            },
            {
                "property": "topic",
                "propertyType": "msg",
                "value": "",
                "valueType": "triggerId"
            }
        ],
        "x": 140,
        "y": 540,
        "wires": [
            [
                "848c101e0f43b693"
            ]
        ]
    },
    {
        "id": "848c101e0f43b693",
        "type": "switch",
        "z": "79866c45b34ebc3c",
        "name": "",
        "property": "payload",
        "propertyType": "msg",
        "rules": [
            {
                "t": "eq",
                "v": "NPO Radio 1",
                "vt": "str"
            },
            {
                "t": "eq",
                "v": "NPO Radio 2",
                "vt": "str"
            },
            {
                "t": "eq",
                "v": "NPO 3FM",
                "vt": "str"
            },
            {
                "t": "eq",
                "v": "NPO Radio 4",
                "vt": "str"
            },
            {
                "t": "eq",
                "v": "Radio 538",
                "vt": "str"
            },
            {
                "t": "eq",
                "v": "Radio 10",
                "vt": "str"
            },
            {
                "t": "eq",
                "v": "Q-Music",
                "vt": "str"
            },
            {
                "t": "eq",
                "v": "Q-Music Christmas",
                "vt": "str"
            },
            {
                "t": "eq",
                "v": "BNR Nieuwsradio",
                "vt": "str"
            },
            {
                "t": "eq",
                "v": "SLAM! FM",
                "vt": "str"
            },
            {
                "t": "eq",
                "v": "100% NL",
                "vt": "str"
            },
            {
                "t": "eq",
                "v": "Veronica",
                "vt": "str"
            },
            {
                "t": "eq",
                "v": "SkyRadio",
                "vt": "str"
            },
            {
                "t": "eq",
                "v": "SubLime FM",
                "vt": "str"
            },
            {
                "t": "eq",
                "v": "KINK",
                "vt": "str"
            }
        ],
        "checkall": "true",
        "repair": false,
        "outputs": 15,
        "x": 370,
        "y": 640,
        "wires": [
            [
                "e514c36156bd0e38"
            ],
            [
                "409803aff588e506"
            ],
            [
                "d75020f84c963da7"
            ],
            [
                "80c0378f4b3e97ab"
            ],
            [
                "392452a311617125"
            ],
            [
                "2b1321f87d6c3f6c"
            ],
            [
                "3f6ca862e1e4616f"
            ],
            [
                "56a8a422790f1a58"
            ],
            [
                "adb99a231aaefade"
            ],
            [
                "8faef14a28899470"
            ],
            [
                "a51c4628fa6f6f34"
            ],
            [
                "74a33411166d5eb7"
            ],
            [
                "d3794b0d4c26f563"
            ],
            [
                "1f027fc65095a11c"
            ],
            [
                "186c9b58834a0eb2"
            ]
        ]
    },
    {
        "id": "f6d3dbf1cd63075c",
        "type": "comment",
        "z": "79866c45b34ebc3c",
        "name": "action when selecting radio station",
        "info": "",
        "x": 180,
        "y": 500,
        "wires": []
    },
    {
        "id": "e514c36156bd0e38",
        "type": "change",
        "z": "79866c45b34ebc3c",
        "name": "",
        "rules": [
            {
                "t": "set",
                "p": "url",
                "pt": "msg",
                "to": "http://icecast.omroep.nl/radio1-bb-aac",
                "tot": "str"
            }
        ],
        "action": "",
        "property": "",
        "from": "",
        "to": "",
        "reg": false,
        "x": 550,
        "y": 540,
        "wires": [
            [
                "d7f77e56d6127dc7"
            ]
        ]
    },
    {
        "id": "409803aff588e506",
        "type": "change",
        "z": "79866c45b34ebc3c",
        "name": "",
        "rules": [
            {
                "t": "set",
                "p": "url",
                "pt": "msg",
                "to": "http://icecast.omroep.nl/radio2-bb-mp3",
                "tot": "str"
            }
        ],
        "action": "",
        "property": "",
        "from": "",
        "to": "",
        "reg": false,
        "x": 550,
        "y": 570,
        "wires": [
            [
                "d7f77e56d6127dc7"
            ]
        ]
    },
    {
        "id": "d75020f84c963da7",
        "type": "change",
        "z": "79866c45b34ebc3c",
        "name": "",
        "rules": [
            {
                "t": "set",
                "p": "url",
                "pt": "msg",
                "to": "http://icecast.omroep.nl/3fm-bb-aac",
                "tot": "str"
            }
        ],
        "action": "",
        "property": "",
        "from": "",
        "to": "",
        "reg": false,
        "x": 550,
        "y": 600,
        "wires": [
            [
                "d7f77e56d6127dc7"
            ]
        ]
    },
    {
        "id": "80c0378f4b3e97ab",
        "type": "change",
        "z": "79866c45b34ebc3c",
        "name": "",
        "rules": [
            {
                "t": "set",
                "p": "url",
                "pt": "msg",
                "to": "http://icecast.omroep.nl/radio4-bb-aac",
                "tot": "str"
            }
        ],
        "action": "",
        "property": "",
        "from": "",
        "to": "",
        "reg": false,
        "x": 550,
        "y": 630,
        "wires": [
            [
                "d7f77e56d6127dc7"
            ]
        ]
    },
    {
        "id": "392452a311617125",
        "type": "change",
        "z": "79866c45b34ebc3c",
        "name": "",
        "rules": [
            {
                "t": "set",
                "p": "url",
                "pt": "msg",
                "to": "http://playerservices.streamtheworld.com/api/livestream-redirect/RADIO538AAC.aac",
                "tot": "str"
            }
        ],
        "action": "",
        "property": "",
        "from": "",
        "to": "",
        "reg": false,
        "x": 550,
        "y": 660,
        "wires": [
            [
                "d7f77e56d6127dc7"
            ]
        ]
    },
    {
        "id": "2b1321f87d6c3f6c",
        "type": "change",
        "z": "79866c45b34ebc3c",
        "name": "",
        "rules": [
            {
                "t": "set",
                "p": "url",
                "pt": "msg",
                "to": "http://playerservices.streamtheworld.com/api/livestream-redirect/RADIO10AAC.aac",
                "tot": "str"
            }
        ],
        "action": "",
        "property": "",
        "from": "",
        "to": "",
        "reg": false,
        "x": 550,
        "y": 690,
        "wires": [
            [
                "d7f77e56d6127dc7"
            ]
        ]
    },
    {
        "id": "3f6ca862e1e4616f",
        "type": "change",
        "z": "79866c45b34ebc3c",
        "name": "",
        "rules": [
            {
                "t": "set",
                "p": "url",
                "pt": "msg",
                "to": "http://icecast-qmusic.cdp.triple-it.nl/Qmusic_nl_live_96.mp3",
                "tot": "str"
            }
        ],
        "action": "",
        "property": "",
        "from": "",
        "to": "",
        "reg": false,
        "x": 550,
        "y": 720,
        "wires": [
            [
                "d7f77e56d6127dc7"
            ]
        ]
    },
    {
        "id": "56a8a422790f1a58",
        "type": "change",
        "z": "79866c45b34ebc3c",
        "name": "",
        "rules": [
            {
                "t": "set",
                "p": "url",
                "pt": "msg",
                "to": "https://icecast-qmusicnl-cdp.triple-it.nl/Qmusic_nl_classics_96.mp3",
                "tot": "str"
            }
        ],
        "action": "",
        "property": "",
        "from": "",
        "to": "",
        "reg": false,
        "x": 550,
        "y": 750,
        "wires": [
            [
                "d7f77e56d6127dc7"
            ]
        ]
    },
    {
        "id": "adb99a231aaefade",
        "type": "change",
        "z": "79866c45b34ebc3c",
        "name": "",
        "rules": [
            {
                "t": "set",
                "p": "url",
                "pt": "msg",
                "to": "http://icecast-bnr.cdp.triple-it.nl/bnr_mp3_128_03",
                "tot": "str"
            }
        ],
        "action": "",
        "property": "",
        "from": "",
        "to": "",
        "reg": false,
        "x": 550,
        "y": 780,
        "wires": [
            [
                "d7f77e56d6127dc7"
            ]
        ]
    },
    {
        "id": "8faef14a28899470",
        "type": "change",
        "z": "79866c45b34ebc3c",
        "name": "",
        "rules": [
            {
                "t": "set",
                "p": "url",
                "pt": "msg",
                "to": "https://stream.slam.nl/web14_mp3",
                "tot": "str"
            }
        ],
        "action": "",
        "property": "",
        "from": "",
        "to": "",
        "reg": false,
        "x": 550,
        "y": 810,
        "wires": [
            [
                "d7f77e56d6127dc7"
            ]
        ]
    },
    {
        "id": "a51c4628fa6f6f34",
        "type": "change",
        "z": "79866c45b34ebc3c",
        "name": "",
        "rules": [
            {
                "t": "set",
                "p": "url",
                "pt": "msg",
                "to": "http://stream.100p.nl/100pctnl.mp3",
                "tot": "str"
            }
        ],
        "action": "",
        "property": "",
        "from": "",
        "to": "",
        "reg": false,
        "x": 550,
        "y": 840,
        "wires": [
            [
                "d7f77e56d6127dc7"
            ]
        ]
    },
    {
        "id": "74a33411166d5eb7",
        "type": "change",
        "z": "79866c45b34ebc3c",
        "name": "",
        "rules": [
            {
                "t": "set",
                "p": "url",
                "pt": "msg",
                "to": "http://playerservices.streamtheworld.com/api/livestream-redirect/VERONICAAAC.aac",
                "tot": "str"
            }
        ],
        "action": "",
        "property": "",
        "from": "",
        "to": "",
        "reg": false,
        "x": 550,
        "y": 870,
        "wires": [
            [
                "d7f77e56d6127dc7"
            ]
        ]
    },
    {
        "id": "d3794b0d4c26f563",
        "type": "change",
        "z": "79866c45b34ebc3c",
        "name": "",
        "rules": [
            {
                "t": "set",
                "p": "url",
                "pt": "msg",
                "to": "http://playerservices.streamtheworld.com/api/livestream-redirect/SKYRADIO.mp3",
                "tot": "str"
            }
        ],
        "action": "",
        "property": "",
        "from": "",
        "to": "",
        "reg": false,
        "x": 550,
        "y": 900,
        "wires": [
            [
                "d7f77e56d6127dc7"
            ]
        ]
    },
    {
        "id": "1f027fc65095a11c",
        "type": "change",
        "z": "79866c45b34ebc3c",
        "name": "",
        "rules": [
            {
                "t": "set",
                "p": "url",
                "pt": "msg",
                "to": "http://stream.sublimefm.nl/SublimeFM_mp3",
                "tot": "str"
            }
        ],
        "action": "",
        "property": "",
        "from": "",
        "to": "",
        "reg": false,
        "x": 550,
        "y": 930,
        "wires": [
            [
                "d7f77e56d6127dc7"
            ]
        ]
    },
    {
        "id": "186c9b58834a0eb2",
        "type": "change",
        "z": "79866c45b34ebc3c",
        "name": "",
        "rules": [
            {
                "t": "set",
                "p": "url",
                "pt": "msg",
                "to": "http://playerservices.streamtheworld.com/api/livestream-redirect/KINK.mp3",
                "tot": "str"
            }
        ],
        "action": "",
        "property": "",
        "from": "",
        "to": "",
        "reg": false,
        "x": 550,
        "y": 960,
        "wires": [
            [
                "d7f77e56d6127dc7"
            ]
        ]
    },
    {
        "id": "6899ab80b8f4ccfd",
        "type": "subflow:9ed9ce7ce8f74ca0",
        "z": "79866c45b34ebc3c",
        "name": "",
        "x": 670,
        "y": 140,
        "wires": []
    },
    {
        "id": "c0e461ba205d827d",
        "type": "subflow:0f710598d50e0596",
        "z": "79866c45b34ebc3c",
        "name": "",
        "x": 670,
        "y": 100,
        "wires": []
    },
    {
        "id": "dd9f2d1024f98824",
        "type": "api-call-service",
        "z": "79866c45b34ebc3c",
        "name": "play media on shield",
        "server": "4ba92433.2478cc",
        "version": 5,
        "debugenabled": false,
        "domain": "media_player",
        "service": "play_media",
        "areaId": [],
        "deviceId": [],
        "entityId": [
            "media_player.shield"
        ],
        "data": "{\"media_content_id\":\"{{{url}}}\",\"media_content_type\":\"music\",\"announce\":\"true\"}",
        "dataType": "json",
        "mergeContext": "",
        "mustacheAltTags": false,
        "outputProperties": [],
        "queue": "none",
        "x": 1040,
        "y": 540,
        "wires": [
            []
        ]
    },
    {
        "id": "d7f77e56d6127dc7",
        "type": "ha-wait-until",
        "z": "79866c45b34ebc3c",
        "name": "wait until shield is not off",
        "server": "4ba92433.2478cc",
        "version": 2,
        "outputs": 1,
        "entityId": "media_player.shield",
        "entityIdFilterType": "exact",
        "property": "state",
        "comparator": "is_not",
        "value": "off",
        "valueType": "str",
        "timeout": "0",
        "timeoutType": "num",
        "timeoutUnits": "seconds",
        "checkCurrentState": true,
        "blockInputOverrides": true,
        "outputProperties": [],
        "entityLocation": "data",
        "entityLocationType": "none",
        "x": 810,
        "y": 540,
        "wires": [
            [
                "dd9f2d1024f98824",
                "8f2b019bbb6a0228"
            ]
        ]
    },
    {
        "id": "f3b88b724a85289b",
        "type": "comment",
        "z": "79866c45b34ebc3c",
        "name": "action based on content",
        "info": "",
        "x": 140,
        "y": 320,
        "wires": []
    },
    {
        "id": "b6c13f3e88d196d9",
        "type": "subflow:ae0491bb.4f1eb",
        "z": "79866c45b34ebc3c",
        "name": "",
        "x": 710,
        "y": 180,
        "wires": []
    },
    {
        "id": "0b032a7e9e924f5e",
        "type": "subflow:ae0491bb.4f1eb",
        "z": "79866c45b34ebc3c",
        "name": "",
        "x": 910,
        "y": 420,
        "wires": []
    },
    {
        "id": "7602bd2250b367d8",
        "type": "ha-wait-until",
        "z": "79866c45b34ebc3c",
        "name": "wait until nvidia shield mediaplayer is on",
        "server": "4ba92433.2478cc",
        "version": 2,
        "outputs": 2,
        "entityId": "media_player.shield",
        "entityIdFilterType": "exact",
        "property": "state",
        "comparator": "is",
        "value": "paused",
        "valueType": "str",
        "timeout": "20",
        "timeoutType": "num",
        "timeoutUnits": "seconds",
        "checkCurrentState": true,
        "blockInputOverrides": true,
        "outputProperties": [],
        "entityLocation": "data",
        "entityLocationType": "none",
        "x": 760,
        "y": 220,
        "wires": [
            [
                "edaa3a9645cc28fa"
            ],
            []
        ]
    },
    {
        "id": "28a8a84a3423603e",
        "type": "api-call-service",
        "z": "79866c45b34ebc3c",
        "name": "play last played radio station",
        "server": "4ba92433.2478cc",
        "version": 5,
        "debugenabled": false,
        "domain": "input_select",
        "service": "select_option",
        "areaId": [],
        "deviceId": [],
        "entityId": [
            "input_select.radio_station"
        ],
        "data": "{\"option\":\"{{payload}}\"}",
        "dataType": "json",
        "mergeContext": "",
        "mustacheAltTags": false,
        "outputProperties": [],
        "queue": "none",
        "x": 1320,
        "y": 220,
        "wires": [
            []
        ]
    },
    {
        "id": "8f2b019bbb6a0228",
        "type": "ha-sensor",
        "z": "79866c45b34ebc3c",
        "name": "last played radio station",
        "entityConfig": "f7917d8c144527e9",
        "version": 0,
        "state": "payload",
        "stateType": "msg",
        "attributes": [],
        "inputOverride": "allow",
        "outputProperties": [],
        "x": 1050,
        "y": 600,
        "wires": [
            []
        ]
    },
    {
        "id": "edaa3a9645cc28fa",
        "type": "api-current-state",
        "z": "79866c45b34ebc3c",
        "name": "get last played radio station",
        "server": "4ba92433.2478cc",
        "version": 3,
        "outputs": 1,
        "halt_if": "",
        "halt_if_type": "str",
        "halt_if_compare": "is",
        "entity_id": "sensor.last_played_radio_station",
        "state_type": "str",
        "blockInputOverrides": false,
        "outputProperties": [
            {
                "property": "payload",
                "propertyType": "msg",
                "value": "",
                "valueType": "entityState"
            }
        ],
        "for": "0",
        "forType": "num",
        "forUnits": "minutes",
        "override_topic": false,
        "state_location": "payload",
        "override_payload": "msg",
        "entity_location": "data",
        "override_data": "msg",
        "x": 1060,
        "y": 220,
        "wires": [
            [
                "28a8a84a3423603e"
            ]
        ]
    },
    {
        "id": "4ba92433.2478cc",
        "type": "server",
        "name": "Home Assistant",
        "version": 5,
        "addon": false,
        "rejectUnauthorizedCerts": false,
        "ha_boolean": "y|yes|true|on|home|open",
        "connectionDelay": true,
        "cacheJson": true,
        "heartbeat": true,
        "heartbeatInterval": "30",
        "areaSelector": "friendlyName",
        "deviceSelector": "friendlyName",
        "entitySelector": "friendlyName",
        "statusSeparator": "at: ",
        "statusYear": "hidden",
        "statusMonth": "short",
        "statusDay": "numeric",
        "statusHourCycle": "h23",
        "statusTimeFormat": "h:m",
        "enableGlobalContextStore": true
    },
    {
        "id": "f7917d8c144527e9",
        "type": "ha-entity-config",
        "server": "4ba92433.2478cc",
        "deviceConfig": "",
        "name": "last played radio station",
        "version": "6",
        "entityType": "sensor",
        "haConfig": [
            {
                "property": "name",
                "value": "last played radio station"
            },
            {
                "property": "icon",
                "value": ""
            },
            {
                "property": "entity_category",
                "value": ""
            },
            {
                "property": "entity_picture",
                "value": ""
            },
            {
                "property": "device_class",
                "value": ""
            },
            {
                "property": "unit_of_measurement",
                "value": ""
            },
            {
                "property": "state_class",
                "value": ""
            }
        ],
        "resend": false,
        "debugEnabled": false
    }
]