[
    {
        "id": "ae0491bb.4f1eb",
        "type": "subflow",
        "name": "tv_screen_off_mode_on",
        "info": "",
        "category": "",
        "in": [
            {
                "x": 40,
                "y": 100,
                "wires": [
                    {
                        "id": "8818e636f63e70c7"
                    },
                    {
                        "id": "9c8540912fe0314a"
                    },
                    {
                        "id": "4d611ca80c166571"
                    },
                    {
                        "id": "e324372da3a76b29"
                    }
                ]
            }
        ],
        "out": [],
        "env": [],
        "meta": {},
        "color": "#DDAA99"
    },
    {
        "id": "be65f0d63b84b58c",
        "type": "api-call-service",
        "z": "ae0491bb.4f1eb",
        "name": "turn on shield",
        "server": "4ba92433.2478cc",
        "version": 5,
        "debugenabled": false,
        "domain": "media_player",
        "service": "turn_on",
        "areaId": [],
        "deviceId": [
            "aa1a5fa6d13fc3224345d871874f8619"
        ],
        "entityId": [
            "media_player.shield"
        ],
        "data": "",
        "dataType": "jsonata",
        "mergeContext": "",
        "mustacheAltTags": false,
        "outputProperties": [],
        "queue": "none",
        "x": 380,
        "y": 160,
        "wires": [
            []
        ]
    },
    {
        "id": "87a4edd77543d7f3",
        "type": "api-call-service",
        "z": "ae0491bb.4f1eb",
        "name": "turn on input boolean music",
        "server": "4ba92433.2478cc",
        "version": 5,
        "debugenabled": false,
        "domain": "input_boolean",
        "service": "turn_on",
        "areaId": [],
        "deviceId": [],
        "entityId": [
            "input_boolean.music"
        ],
        "data": "",
        "dataType": "json",
        "mergeContext": "",
        "mustacheAltTags": false,
        "outputProperties": [],
        "queue": "none",
        "x": 480,
        "y": 220,
        "wires": [
            []
        ]
    },
    {
        "id": "9c8540912fe0314a",
        "type": "api-current-state",
        "z": "ae0491bb.4f1eb",
        "name": "state input boolean tv off",
        "server": "4ba92433.2478cc",
        "version": 3,
        "outputs": 2,
        "halt_if": "off",
        "halt_if_type": "str",
        "halt_if_compare": "is",
        "entity_id": "input_boolean.music",
        "state_type": "str",
        "blockInputOverrides": true,
        "outputProperties": [
            {
                "property": "payload",
                "propertyType": "msg",
                "value": "",
                "valueType": "entityState"
            },
            {
                "property": "data",
                "propertyType": "msg",
                "value": "",
                "valueType": "entity"
            }
        ],
        "for": 0,
        "forType": "num",
        "forUnits": "minutes",
        "x": 230,
        "y": 220,
        "wires": [
            [
                "87a4edd77543d7f3"
            ],
            []
        ]
    },
    {
        "id": "8818e636f63e70c7",
        "type": "api-current-state",
        "z": "ae0491bb.4f1eb",
        "name": "state shield off",
        "server": "4ba92433.2478cc",
        "version": 3,
        "outputs": 2,
        "halt_if": "off",
        "halt_if_type": "str",
        "halt_if_compare": "is",
        "entity_id": "media_player.shield",
        "state_type": "str",
        "blockInputOverrides": false,
        "outputProperties": [
            {
                "property": "payload",
                "propertyType": "msg",
                "value": "",
                "valueType": "entityState"
            },
            {
                "property": "data",
                "propertyType": "msg",
                "value": "",
                "valueType": "entity"
            }
        ],
        "for": "0",
        "forType": "num",
        "forUnits": "minutes",
        "override_topic": false,
        "state_location": "payload",
        "override_payload": "msg",
        "entity_location": "data",
        "override_data": "msg",
        "x": 200,
        "y": 160,
        "wires": [
            [
                "be65f0d63b84b58c"
            ],
            []
        ]
    },
    {
        "id": "4d611ca80c166571",
        "type": "api-call-service",
        "z": "ae0491bb.4f1eb",
        "name": "turn on receiver",
        "server": "4ba92433.2478cc",
        "version": 5,
        "debugenabled": false,
        "domain": "remote",
        "service": "send_command",
        "areaId": [],
        "deviceId": [
            "34a73fe47cda5c964dcb946e48f8a307"
        ],
        "entityId": [
            "remote.harmony_hub_01"
        ],
        "data": "{\"device\":\"53126254\",\"command\":\"PowerOn\"}",
        "dataType": "json",
        "mergeContext": "",
        "mustacheAltTags": false,
        "outputProperties": [],
        "queue": "none",
        "x": 200,
        "y": 280,
        "wires": [
            []
        ]
    },
    {
        "id": "0cb67556a76c3eb6",
        "type": "api-call-service",
        "z": "ae0491bb.4f1eb",
        "name": "turn off screen",
        "server": "4ba92433.2478cc",
        "version": 5,
        "debugenabled": false,
        "domain": "webostv",
        "service": "command",
        "areaId": [],
        "deviceId": [],
        "entityId": [
            "media_player.lg_webos_smart_tv"
        ],
        "data": "{\"command\":\"com.webos.service.tvpower/power/turnOffScreen\"}",
        "dataType": "json",
        "mergeContext": "",
        "mustacheAltTags": false,
        "outputProperties": [],
        "queue": "none",
        "x": 740,
        "y": 100,
        "wires": [
            []
        ]
    },
    {
        "id": "e324372da3a76b29",
        "type": "ha-wait-until",
        "z": "ae0491bb.4f1eb",
        "name": "wait until tv mediaplayer is on",
        "server": "4ba92433.2478cc",
        "version": 2,
        "outputs": 1,
        "entityId": "media_player.lg_webos_smart_tv",
        "entityIdFilterType": "exact",
        "property": "state",
        "comparator": "is_not",
        "value": "off",
        "valueType": "str",
        "timeout": "0",
        "timeoutType": "num",
        "timeoutUnits": "seconds",
        "checkCurrentState": true,
        "blockInputOverrides": true,
        "outputProperties": [],
        "entityLocation": "data",
        "entityLocationType": "none",
        "x": 240,
        "y": 100,
        "wires": [
            [
                "19bc30746baef510"
            ]
        ]
    },
    {
        "id": "19bc30746baef510",
        "type": "api-current-state",
        "z": "ae0491bb.4f1eb",
        "name": "harmony activity is scherm uit",
        "server": "4ba92433.2478cc",
        "version": 3,
        "outputs": 2,
        "halt_if": "Scherm Uit",
        "halt_if_type": "str",
        "halt_if_compare": "is",
        "entity_id": "input_select.entertainment_activity",
        "state_type": "str",
        "blockInputOverrides": false,
        "outputProperties": [
            {
                "property": "payload",
                "propertyType": "msg",
                "value": "",
                "valueType": "entityState"
            },
            {
                "property": "data",
                "propertyType": "msg",
                "value": "",
                "valueType": "entity"
            }
        ],
        "for": "0",
        "forType": "num",
        "forUnits": "minutes",
        "override_topic": false,
        "state_location": "payload",
        "override_payload": "msg",
        "entity_location": "data",
        "override_data": "msg",
        "x": 510,
        "y": 100,
        "wires": [
            [
                "0cb67556a76c3eb6"
            ],
            []
        ]
    },
    {
        "id": "54d7a449b5482909",
        "type": "comment",
        "z": "ae0491bb.4f1eb",
        "name": "turn on tv and turn off screen for low energy usage",
        "info": "",
        "x": 210,
        "y": 40,
        "wires": []
    },
    {
        "id": "4ba92433.2478cc",
        "type": "server",
        "name": "Home Assistant",
        "version": 5,
        "addon": false,
        "rejectUnauthorizedCerts": false,
        "ha_boolean": "y|yes|true|on|home|open",
        "connectionDelay": true,
        "cacheJson": true,
        "heartbeat": true,
        "heartbeatInterval": "30",
        "areaSelector": "friendlyName",
        "deviceSelector": "friendlyName",
        "entitySelector": "friendlyName",
        "statusSeparator": "at: ",
        "statusYear": "hidden",
        "statusMonth": "short",
        "statusDay": "numeric",
        "statusHourCycle": "h23",
        "statusTimeFormat": "h:m",
        "enableGlobalContextStore": true
    }
]